Metadata-Version: 2.1
Name: biliget0
Version: 0.0.1
Summary: Biliget on phone.
Home-page: https://github.com/lixiaobai468/biliget
Author: lixiaobai
Author-email: 18108274905@163.com
License: UNKNOWN
Platform: UNKNOWN
Classifier: Programming Language :: Python :: 3
Classifier: License :: OSI Approved :: MIT License
Classifier: Operating System :: OS Independent
